{"stats":{"minecraft:killed_by":{"minecraft:skeleton":3,"minecraft:creeper":1,"minecraft:zombie":2,"minecraft:pillager":1},"minecraft:killed":{"minecraft:rabbit":1,"minecraft:spider":1,"minecraft:zombie":9},"minecraft:used":{"minecraft:diorite":4,"minecraft:stone_sword":87,"minecraft:stone_pickaxe":392,"minecraft:baked_potato":20,"minecraft:oak_planks":160,"minecraft:wooden_pickaxe":14,"minecraft:iron_chestplate":1,"minecraft:torch":42,"minecraft:dirt":88,"minecraft:crafting_table":2,"minecraft:carrot":1,"minecraft:wooden_axe":48,"minecraft:apple":2,"minecraft:iron_helmet":1,"minecraft:iron_boots":1,"minecraft:stone_axe":44,"minecraft:wooden_sword":25,"minecraft:cobblestone":36,"minecraft:iron_leggings":1},"minecraft:mined":{"minecraft:dandelion":1,"minecraft:crafting_table":4,"minecraft:torch":4,"minecraft:granite":2,"minecraft:grass_block":20,"minecraft:cobblestone":14,"minecraft:copper_ore":6,"minecraft:oak_planks":14,"minecraft:diorite":14,"minecraft:oxeye_daisy":1,"minecraft:wall_torch":2,"minecraft:birch_log":6,"minecraft:iron_ore":12,"minecraft:wheat":1,"minecraft:andesite":6,"minecraft:birch_leaves":2,"minecraft:grass":33,"minecraft:oak_log":70,"minecraft:coal_ore":89,"minecraft:gravel":5,"minecraft:dirt":40,"minecraft:stone":242,"minecraft:oak_leaves":74},"minecraft:custom":{"minecraft:interact_with_furnace":19,"minecraft:mob_kills":11,"minecraft:interact_with_crafting_table":14,"minecraft:leave_game":2,"minecraft:time_since_death":7095,"minecraft:sleep_in_bed":8,"minecraft:time_since_rest":7115,"minecraft:sprint_one_cm":225211,"minecraft:damage_taken":4088,"minecraft:walk_one_cm":302690,"minecraft:drop":47,"minecraft:damage_dealt":2035,"minecraft:swim_one_cm":489,"minecraft:fly_one_cm":339629,"minecraft:open_chest":11,"minecraft:crouch_one_cm":10463,"minecraft:play_time":102503,"minecraft:deaths":11,"minecraft:sneak_time":3200,"minecraft:walk_under_water_one_cm":333,"minecraft:jump":2073,"minecraft:walk_on_water_one_cm":2358,"minecraft:total_world_time":102503,"minecraft:fall_one_cm":95405},"minecraft:broken":{"minecraft:stone_pickaxe":3,"minecraft:wooden_sword":1},"minecraft:dropped":{"minecraft:stone_sword":1,"minecraft:wheat":1,"minecraft:raw_iron":4,"minecraft:cobblestone":32,"minecraft:stick":8,"minecraft:oxeye_daisy":1,"minecraft:dirt":1,"minecraft:dandelion":1},"minecraft:picked_up":{"minecraft:wooden_axe":5,"minecraft:birch_log":12,"minecraft:crafting_table":15,"minecraft:wheat":1,"minecraft:andesite":12,"minecraft:wooden_pickaxe":1,"minecraft:oak_log":224,"minecraft:string":2,"minecraft:dirt":92,"minecraft:raw_copper":101,"minecraft:wooden_sword":2,"minecraft:bone":9,"minecraft:apple":2,"minecraft:wheat_seeds":8,"minecraft:iron_ingot":24,"minecraft:rabbit_hide":4,"minecraft:beef":1,"minecraft:stone_pickaxe":11,"minecraft:oak_planks":123,"minecraft:stick":17,"minecraft:raw_iron":40,"minecraft:torch":61,"minecraft:dandelion":1,"minecraft:gravel":14,"minecraft:diorite":49,"minecraft:carrot":1,"minecraft:spider_eye":1,"minecraft:stone_sword":7,"minecraft:rotten_flesh":13,"minecraft:stone_axe":6,"minecraft:granite":6,"minecraft:baked_potato":66,"minecraft:oak_sapling":15,"minecraft:coal":450,"minecraft:cobblestone":1082,"minecraft:oxeye_daisy":1},"minecraft:crafted":{"minecraft:oak_planks":184,"minecraft:iron_helmet":1,"minecraft:baked_potato":19,"minecraft:stone_axe":2,"minecraft:iron_chestplate":1,"minecraft:iron_boots":1,"minecraft:stick":48,"minecraft:stone_pickaxe":5,"minecraft:wooden_axe":1,"minecraft:stone_sword":3,"minecraft:iron_leggings":1,"minecraft:torch":56}},"DataVersion":3120}